baidu_tts/__init__.py
baidu_tts-0.0.3.dist-info/DESCRIPTION.rst
baidu_tts-0.0.3.dist-info/METADATA
baidu_tts-0.0.3.dist-info/RECORD
baidu_tts-0.0.3.dist-info/WHEEL
baidu_tts-0.0.3.dist-info/metadata.json
baidu_tts-0.0.3.dist-info/top_level.txt
