Metadata-Version: 2.0
Name: baidu-tts
Version: 0.0.3
Summary: A Python lib of Baidu TTS.
Home-page: http://github.com/yetone/baidu_tts
Author: yetone
Author-email: yetoneful@gmail.com
License: MIT License
Keywords: TTS,sound,Baidu
Platform: any
Requires-Dist: requests (>=2.7.0)
